pydocker_util/__init__.py
pydocker_util/docker_util.py
pydocker_util-1.0.0.dist-info/LICENSE
pydocker_util-1.0.0.dist-info/METADATA
pydocker_util-1.0.0.dist-info/WHEEL
pydocker_util-1.0.0.dist-info/top_level.txt
pydocker_util-1.0.0.dist-info/zip-safe
pydocker_util-1.0.0.dist-info/RECORD
